claude_workshop-2.8.0.dist-info/licenses/LICENSE
src/__init__.py
src/cli.py
src/config.py
src/display.py
src/export.py
src/git_utils.py
src/jsonl_parser.py
src/migrate.py
src/models.py
src/project_detection.py
src/schema.sql
src/storage.py
src/storage_sqlite.py
src/claude_templates/CLAUDE.md
src/claude_templates/README.md
src/claude_templates/settings.json
src/claude_templates/workshop-pre-compact.sh
src/claude_templates/workshop-session-end.sh
src/claude_templates/workshop-session-start.sh
src/claude_templates/commands/workshop.sh
src/storage/__init__.py
src/storage/base.py
src/storage/entries.py
src/storage/import_history.py
src/storage/preferences_state.py
src/storage/raw_messages.py
src/storage/sessions.py
src/web/__init__.py
src/web/app.py
src/web/templates/base.html
src/web/templates/conversation.html
src/web/templates/dashboard.html
src/web/templates/edit.html
src/web/templates/entries.html
src/web/templates/messages.html
src/web/templates/new.html
src/web/templates/settings.html
src/web/templates/view.html
src/web/templates/view_message.html
claude_workshop-2.8.0.dist-info/METADATA
claude_workshop-2.8.0.dist-info/WHEEL
claude_workshop-2.8.0.dist-info/entry_points.txt
claude_workshop-2.8.0.dist-info/top_level.txt
claude_workshop-2.8.0.dist-info/RECORD
