Metadata-Version: 2.4
Name: claude-workshop
Version: 2.8.0
Summary: Persistent context and memory tool for Claude Code sessions
Author: Claude & Zach
Author-email: Claude & Zach Swift <zachswift615@gmail.com>
License: MIT
Project-URL: Homepage, https://github.com/zachswift615/workshop
Project-URL: Repository, https://github.com/zachswift615/workshop
Project-URL: Issues, https://github.com/zachswift615/workshop/issues
Keywords: claude,claude-code,context,memory,notes,decisions,development-tools,cli
Classifier: Development Status :: 4 - Beta
Classifier: Intended Audience :: Developers
Classifier: Topic :: Software Development :: Documentation
Classifier: Topic :: Software Development :: Libraries :: Application Frameworks
Classifier: License :: OSI Approved :: MIT License
Classifier: Programming Language :: Python :: 3
Classifier: Programming Language :: Python :: 3.8
Classifier: Programming Language :: Python :: 3.9
Classifier: Programming Language :: Python :: 3.10
Classifier: Programming Language :: Python :: 3.11
Classifier: Programming Language :: Python :: 3.12
Classifier: Operating System :: OS Independent
Classifier: Environment :: Console
Requires-Python: >=3.8
License-File: LICENSE
Requires-Dist: click>=8.1.0
Requires-Dist: rich>=13.0.0
Requires-Dist: python-dateutil>=2.8.0
Requires-Dist: sqlalchemy>=2.0.0
Provides-Extra: dev
Requires-Dist: pytest>=7.0.0; extra == "dev"
Requires-Dist: pytest-cov>=4.0.0; extra == "dev"
Requires-Dist: build>=0.10.0; extra == "dev"
Requires-Dist: twine>=4.0.0; extra == "dev"
Provides-Extra: web
Requires-Dist: flask>=2.0.0; extra == "web"
Provides-Extra: llm
Requires-Dist: anthropic>=0.18.0; extra == "llm"
Requires-Dist: openai>=1.0.0; extra == "llm"
Provides-Extra: cloud
Requires-Dist: workshop-client>=0.1.0; extra == "cloud"
Requires-Dist: psycopg2-binary>=2.9.0; extra == "cloud"
Requires-Dist: asyncpg>=0.29.0; extra == "cloud"
Dynamic: author
Dynamic: license-file
Dynamic: requires-python
